networksage_tools/common_utilities/__init__.py
networksage_tools/common_utilities/dnsservice.py
networksage_tools/common_utilities/iputils.py
networksage_tools/common_utilities/packet.py
networksage_tools/common_utilities/secflow.py
networksage_tools/common_utilities/utilities.py
networksage_tools/converter/__init__.py
networksage_tools/converter/convert.py
networksage_tools/converter/generic_flowutils.py
networksage_tools/converter/interflow.py
networksage_tools/converter/interflowutils.py
networksage_tools/converter/pcaputils.py
networksage_tools/converter/tests.py
networksage_tools/converter/zeekflow.py
networksage_tools/converter/zeekutils.py
networksage_tools/converter/tests/expectedOutputs/testCase10_oneFlowIsProcessable.conn.sf
networksage_tools/converter/tests/expectedOutputs/testCase12_icmp_plus_others.conn.sf
networksage_tools/converter/tests/expectedOutputs/testCase13_mtbDotcom_bangInPlaceOfDot_filtered.sf
networksage_tools/converter/tests/expectedOutputs/testCase14_faturasatacada_phish_with_nonephemeral_dport9999_filtered.sf
networksage_tools/converter/tests/expectedOutputs/testCase15_chromeWin10StartChromeBrowser_JSON.conn.sf
networksage_tools/converter/tests/expectedOutputs/testCase16_chromeWin10VisitAmazonScamaDotCom_JSON.conn.sf
networksage_tools/converter/tests/expectedOutputs/testCase18_oneFlowIsProcessable_JSON.conn.sf
networksage_tools/converter/tests/expectedOutputs/testCase19_icmp_plus_others_JSON.conn.sf
networksage_tools/converter/tests/expectedOutputs/testCase1_chromeWin10StartChromeBrowser_filtered.sf
networksage_tools/converter/tests/expectedOutputs/testCase20_oneFlowIsProcessable_newstyle_JSON.conn.sf
networksage_tools/converter/tests/expectedOutputs/testCase21_icmp_plus_others_newstyle_JSON.conn.sf
networksage_tools/converter/tests/expectedOutputs/testCase2_chromeWin10VisitAmazonScamaDotCom_filtered.sf
networksage_tools/converter/tests/expectedOutputs/testCase4_onePacketIsProcessable_filtered.sf
networksage_tools-1.1.4.dist-info/LICENSE
networksage_tools-1.1.4.dist-info/METADATA
networksage_tools-1.1.4.dist-info/WHEEL
networksage_tools-1.1.4.dist-info/top_level.txt
networksage_tools-1.1.4.dist-info/RECORD
