Metadata-Version: 2.1
Name: networksage-tools
Version: 1.1.4
Summary: Functionality to support usage and development on top of the NetworkSage platform.
Home-page: https://github.com/NetworkSage/public-tools
Author: David Pearson
Author-email: david@seclarity.io
Project-URL: Bug Tracker, https://github.com/NetworkSage/public-tools/issues
Classifier: Programming Language :: Python :: 3
Classifier: License :: OSI Approved :: Apache Software License
Classifier: Operating System :: MacOS :: MacOS X
Classifier: Operating System :: POSIX :: Linux
Requires-Python: >=3.9
License-File: LICENSE
Requires-Dist: ipaddress (>=1.0.23)
Requires-Dist: jmespath (>=0.10.0)
Requires-Dist: pcapy (>=0.11.4)
Requires-Dist: pcapy-ng (>=1.0.4)
Requires-Dist: pathlib (>=1.0.1)
Requires-Dist: networksage-wrappers (>=0.9.3)
Requires-Dist: python-dateutil (>=2.8.2)
Requires-Dist: python-magic (>=0.4.24)
Requires-Dist: six (>=1.16.0)
Requires-Dist: urllib3 (>=1.26.6)
Requires-Dist: filelock (>=3.4.0)
Requires-Dist: jsonify (>=0.5)
Requires-Dist: argparse (>=1.4.0)
